hyperlm/__init__.py
hyperlm/checkpoint.pt
hyperlm/hyper_label_model.py
hyperlm/loss.py
hyperlm-0.0.5.dist-info/LICENSE
hyperlm-0.0.5.dist-info/METADATA
hyperlm-0.0.5.dist-info/WHEEL
hyperlm-0.0.5.dist-info/top_level.txt
hyperlm-0.0.5.dist-info/RECORD
