Metadata-Version: 2.1
Name: hyperlm
Version: 0.0.5
Summary: A hyper label model to aggregate weak labels from multiple weak supervision sources to infer the ground-truth labels in a single forward pass
Author-email: Renzhi Wu <renzhiwu@gatech.edu>
Project-URL: Homepage, https://github.com/wurenzhi/hyper_label_model
Project-URL: Bug Tracker, https://github.com/wurenzhi/hyper_label_model/issues
Classifier: Programming Language :: Python :: 3
Classifier: License :: OSI Approved :: MIT License
Classifier: Operating System :: OS Independent
Requires-Python: >=3.6
License-File: LICENSE
Requires-Dist: scipy
Requires-Dist: numpy
Requires-Dist: torch (>=1.9.0)
